Metadata-Version: 2.4
Name: cf-remote
Version: 0.8.7
Summary: Tooling to deploy CFEngine (and much more)
Home-page: https://github.com/cfengine/cf-remote
Author: Northern.tech, Inc.
Author-email: contact@northern.tech
Classifier: Programming Language :: Python :: 3
Classifier: License :: OSI Approved :: GNU General Public License v3 (GPLv3)
Classifier: Operating System :: OS Independent
Requires-Python: >=3.5
License-File: LICENSE
Requires-Dist: apache-libcloud>=3.3.1
Dynamic: author
Dynamic: author-email
Dynamic: classifier
Dynamic: description
Dynamic: description-content-type
Dynamic: home-page
Dynamic: license-file
Dynamic: requires-dist
Dynamic: requires-python
Dynamic: summary
